t1d_cpd_benchmark/__init__.py
t1d_cpd_benchmark/datasets/__init__.py
t1d_cpd_benchmark/datasets/obfuscated_data.py
t1d_cpd_benchmark/datasets/processed_data.py
t1d_cpd_benchmark/datasets/raw_data.py
t1d_cpd_benchmark-0.1.5.dist-info/LICENSE
t1d_cpd_benchmark-0.1.5.dist-info/METADATA
t1d_cpd_benchmark-0.1.5.dist-info/WHEEL
t1d_cpd_benchmark-0.1.5.dist-info/top_level.txt
t1d_cpd_benchmark-0.1.5.dist-info/RECORD
