Metadata-Version: 2.1
Name: t1d_cpd_benchmark
Version: 0.1.5
Summary: An open source benchmark for semi-supervised change point detection of type 1 diabetic meals from continuous glucose monitor time series data. Originally created to present to PyData Global 2024 in association with sktime and skchange.
Home-page: https://github.com/Blood-Glucose-Control/t1d-change-point-detection-benchmark
Author: Christopher Risi
Author-email: christopher.risi@uwaterloo.ca
License: MIT
License-File: LICENSE
Requires-Dist: numpy>=1.25.0
Requires-Dist: pandas>=2.0.3
